Metadata-Version: 2.1
Name: versionchecker
Version: 1.0.0
Summary: Check for outdated packages installed on your system and get the latest version number
Home-page: https://github.com/usvimal/versionchecker
Author: Vimal
Author-email: usvimal@gmail.com
License: UNKNOWN
Download-URL: https://github.com/usvimal/versionchecker/archive/1.0.0.tar.gz
Platform: UNKNOWN
Classifier: Programming Language :: Python :: 3
Classifier: License :: OSI Approved :: MIT License
Classifier: Operating System :: OS Independent
